einvoices/__init__.py
einvoices/admin.py
einvoices/apps.py
einvoices/constants.py
einvoices/helpers.py
einvoices/models.py
einvoices/views.py
einvoices/migrations/0001_initial.py
einvoices/migrations/__init__.py
einvoices/services/__init__.py
einvoices/services/invoice_service.py
einvoices/services/xml_service.py
zatca/__init__.py
zatca/admin.py
zatca/apps.py
zatca/models.py
zatca/tests.py
zatca/views.py
zatca/integrations/__init__.py
zatca/integrations/zatca.py
zatca/migrations/0001_initial.py
zatca/migrations/__init__.py
zatca/services/__init__.py
zatca/services/onboarding.py
zatca/services/renewing.py
takamol_einvoicer_test_kit7-0.1.dist-info/LICENSE
takamol_einvoicer_test_kit7-0.1.dist-info/METADATA
takamol_einvoicer_test_kit7-0.1.dist-info/WHEEL
takamol_einvoicer_test_kit7-0.1.dist-info/top_level.txt
takamol_einvoicer_test_kit7-0.1.dist-info/RECORD
